COPYING
MANIFEST.in
README.md
setup.py
etc/haproxy/haproxy.cfg
etc/init/swftp-ftp.conf
etc/init/swftp-sftp.conf
etc/init.d/swftp-ftp
etc/init.d/swftp-sftp
etc/supervisor/conf.d/swftp.conf
etc/swftp/swftp.conf.sample
etc/swftp/test.conf.sample
swftp/__init__.py
swftp/auth.py
swftp/idle_timeout.py
swftp/logging.py
swftp/report.py
swftp/statsd.py
swftp/swift.py
swftp/swiftfilesystem.py
swftp/utils.py
swftp.egg-info/PKG-INFO
swftp.egg-info/SOURCES.txt
swftp.egg-info/dependency_links.txt
swftp.egg-info/entry_points.txt
swftp.egg-info/not-zip-safe
swftp.egg-info/requires.txt
swftp.egg-info/top_level.txt
swftp/ftp/__init__.py
swftp/ftp/server.py
swftp/ftp/service.py
swftp/sftp/__init__.py
swftp/sftp/server.py
swftp/sftp/service.py
swftp/sftp/swiftdirectory.py
swftp/sftp/swiftfile.py
swftp/test/__init__.py
swftp/test/test.conf
swftp/test/test_id_rsa
swftp/test/test_id_rsa.pub
swftp/test/functional/__init__.py
swftp/test/functional/test_ftp.py
swftp/test/functional/test_sftp.py
swftp/test/unit/__init__.py
swftp/test/unit/test_auth.py
swftp/test/unit/test_ftp.py
swftp/test/unit/test_sftp.py
swftp/test/unit/test_swift.py
swftp/test/unit/test_utils.py
twisted/plugins/dropin.cache
twisted/plugins/swftp_ftp.py
twisted/plugins/swftp_ftp.pyc
twisted/plugins/swftp_sftp.py
twisted/plugins/swftp_sftp.pyc