Metadata-Version: 1.1
Name: swftp
Version: 1.0.7
Summary: SwFTP is an FTP and SFTP interface for Openstack Object
Home-page: https://github.com/softlayer/swftp
Author: Kevin McDonald
Author-email: kmcdonald@softlayer.com
License: MIT
Platform: UNKNOWN
Classifier: Environment :: Console
Classifier: Operating System :: OS Independent
Classifier: Environment :: No Input/Output (Daemon)
Classifier: Framework :: Twisted
Classifier: License :: OSI Approved :: MIT License
Classifier: Topic :: Internet :: File Transfer Protocol (FTP)
Classifier: Programming Language :: Python
Classifier: Programming Language :: Python :: 2.6
Classifier: Programming Language :: Python :: 2.7
